EtherTDD-0.1.4.dist-info/RECORD
EtherTDD-0.1.4.dist-info/pbr.json
EtherTDD-0.1.4.dist-info/WHEEL
EtherTDD-0.1.4.dist-info/DESCRIPTION.rst
EtherTDD-0.1.4.dist-info/top_level.txt
EtherTDD-0.1.4.dist-info/metadata.json
EtherTDD-0.1.4.dist-info/METADATA
ethertdd/__init__.py
