Metadata-Version: 2.0
Name: EtherTDD
Version: 0.1.4
Summary: Ethereum unit testing tool.
Home-page: https://github.com/ryepdx/ethertdd.py/
Author: Ryan Casey
Author-email: ryepdx@gmail.com
License: UNKNOWN
Platform: UNKNOWN
Requires: ethereum
